dbbasic_accounts/__init__.py
dbbasic_accounts/accounts.py
dbbasic_accounts/admin.py
dbbasic_accounts/cli.py
dbbasic_accounts/passwd.py
dbbasic_accounts/tsv_db.py
dbbasic_accounts/api/__init__.py
dbbasic_accounts/api/accounts/__init__.py
dbbasic_accounts/api/accounts/users.py
dbbasic_accounts-0.1.1.dist-info/licenses/LICENSE
tests/__init__.py
tests/test_accounts.py
tests/test_passwd.py
dbbasic_accounts-0.1.1.dist-info/METADATA
dbbasic_accounts-0.1.1.dist-info/WHEEL
dbbasic_accounts-0.1.1.dist-info/entry_points.txt
dbbasic_accounts-0.1.1.dist-info/top_level.txt
dbbasic_accounts-0.1.1.dist-info/RECORD
